py_vk_bot_api/__init__.py
py_vk_bot_api/api.py
py_vk_bot_api/botslongpoll.py
py_vk_bot_api/exceptions.py
py_vk_bot_api/session.py
py_vk_bot_api/upload.py
py_vk_bot_api-1.0.dist-info/LICENSE
py_vk_bot_api-1.0.dist-info/METADATA
py_vk_bot_api-1.0.dist-info/WHEEL
py_vk_bot_api-1.0.dist-info/top_level.txt
py_vk_bot_api-1.0.dist-info/RECORD
