Metadata-Version: 1.1
Name: py_vk_bot_api
Version: 1.0
Summary: Python vk.com API wrapper
Home-page: https://github.com/Airkek/py_vk_bot_api/
Author: Airkek
Author-email: antonyblack05@gmail.com
License: UNKNOWN
Platform: UNKNOWN
Classifier: Programming Language :: Python :: 3.7
Classifier: License :: OSI Approved :: MIT License
Classifier: Operating System :: OS Independent
